tmd/__init__.py
tmd/processor.py
truemapdata-0.1.3.dist-info/licenses/LICENSE
truemapdata-0.1.3.dist-info/METADATA
truemapdata-0.1.3.dist-info/WHEEL
truemapdata-0.1.3.dist-info/entry_points.txt
truemapdata-0.1.3.dist-info/top_level.txt
truemapdata-0.1.3.dist-info/RECORD
