Metadata-Version: 2.4
Name: truemapdata
Version: 0.1.3
Summary: A library for processing TMD files and visualizing height maps
Author-email: Antoine Boucher <antoine@antoineboucher.info>
Maintainer-email: Antoine Boucher <antoine@antoineboucher.info>
License: MIT
Project-URL: Homepage, https://github.com/ETSTribology/TrueMapData
Project-URL: Bug Tracker, https://github.com/ETSTribology/TrueMapData/issues
Project-URL: Documentation, https://etstribology.github.io/TrueMapData/
Keywords: tmd,heightmap,3d,visualization,truemap,gelsight
Classifier: Development Status :: 4 - Beta
Classifier: Intended Audience :: Science/Research
Classifier: Programming Language :: Python :: 3
Classifier: Programming Language :: Python :: 3.8
Classifier: Programming Language :: Python :: 3.9
Classifier: Programming Language :: Python :: 3.10
Classifier: Programming Language :: Python :: 3.11
Classifier: Programming Language :: Python :: 3.12
Classifier: License :: OSI Approved :: MIT License
Classifier: Operating System :: OS Independent
Classifier: Topic :: Scientific/Engineering :: Visualization
Classifier: Topic :: Multimedia :: Graphics :: 3D Modeling
Requires-Python: >=3.8
License-File: LICENSE
Requires-Dist: numpy>=1.20.0
Requires-Dist: plotly>=5.10.0
Requires-Dist: pillow>=9.0.0
Requires-Dist: matplotlib>=3.5.0
Requires-Dist: seaborn>=0.12.0
Requires-Dist: scipy>=1.8.0
Requires-Dist: rich>=12.0.0
Requires-Dist: typer>=0.7.0
Requires-Dist: opencv-python>=4.5.0
Requires-Dist: meshio>=5.0.0
Provides-Extra: dev
Requires-Dist: pytest>=7.0.0; extra == "dev"
Requires-Dist: pytest-cov>=4.0.0; extra == "dev"
Requires-Dist: black>=23.0.0; extra == "dev"
Requires-Dist: isort>=5.10.0; extra == "dev"
Requires-Dist: flake8>=5.0.0; extra == "dev"
Requires-Dist: mypy>=1.0.0; extra == "dev"
Requires-Dist: tox>=4.0.0; extra == "dev"
Requires-Dist: pre-commit>=3.0.0; extra == "dev"
Provides-Extra: docs
Requires-Dist: mkdocs>=1.4.0; extra == "docs"
Requires-Dist: mkdocs-material>=9.0.0; extra == "docs"
Requires-Dist: mkdocstrings>=0.20.0; extra == "docs"
Requires-Dist: mkdocstrings-python>=1.0.0; extra == "docs"
Requires-Dist: pymdown-extensions>=9.0; extra == "docs"
Requires-Dist: pygments>=2.13.0; extra == "docs"
Requires-Dist: mkdocs-git-revision-date-localized-plugin>=1.0.0; extra == "docs"
Provides-Extra: viz
Requires-Dist: pyvista>=0.37.0; extra == "viz"
Provides-Extra: full
Requires-Dist: truemapdata[dev,docs,viz]; extra == "full"
Dynamic: license-file
